Vstore/Vstore.py
Vstore/__init__.py
Vstore-0.1.0.dist-info/LICENSE
Vstore-0.1.0.dist-info/METADATA
Vstore-0.1.0.dist-info/WHEEL
Vstore-0.1.0.dist-info/top_level.txt
Vstore-0.1.0.dist-info/RECORD
