Metadata-Version: 2.1
Name: Vstore
Version: 0.1.0
Summary: variable save/load package by Point from Symbs Studios
Author-email: Point Symbs <point.symbs@gmail.com>
Classifier: Programming Language :: Python :: 3
Classifier: License :: OSI Approved :: MIT License
Classifier: Operating System :: OS Independent
Requires-Python: >=3.11
License-File: LICENSE
